{"intents": [
  {"tag": "greetings",
    "patterns": ["hello" ," hey", "hi", "good day", "Greetings","how is it going?"],
    "responses": ["Hello!", "Hey!", "what can I do for you?"]
  },

  {"tag": "goodbye",
    "patterns": ["cya" ,"See you later!","Goodbye", "I am Leaving","Have a good day ","bye", "cao", "see ya"],
    "responses": ["Sad to see you go!", "Talk to you later", "Goodbye!"]
  },
  {"tag": "age",
    "patterns": [ "how old is shashika", "what is your age", "how old are you", "age?"],
    "responses": ["My owner shashika is 24 years old!", "24 years!"]
  },
   {"tag": "findings",
    "patterns": [ "how are you", "what is up to do", "what about these days"],
    "responses": ["Me and Shashika is doing good men", "I'm doing good"]
  },
  {"tag": "name",
    "patterns": ["what is your name" ,"what should I call you", "whats your name?", "who are you", "Can you tell me your age?"],
    "responses": ["you can call me  Kahtzbot!.", "I'm Kahtzbot!", "I'm Kahtzbot the assistance of Shashika"]
  },
  {"tag": "shop",
    "patterns": ["I'd like to buy Something", "what are your products?", "what do you recommend?", "what are you selling"],
    "responses": ["We have different set of Technology based publications  "]
  },
  {"tag": "hours",
    "patterns": ["when are you guys open" ,"what are your hours", "hours operation"],
    "responses": ["24/7"]
  },
  {"tag": "stocks",
    "patterns": ["what stocks do I own?" ,"how are are my shares? ", "what companies am I investing in", "what am I doing"],
    "responses": ["You own the Following  shares: ABBY, AAPL, FB,NVDA and an ETF of the S&P 500 Index!"]
  }
]}